Ctoolbox/__init__.py
Ctoolbox/cfg_editor/__init__.py
Ctoolbox/cfg_editor/cfg_generator.py
Ctoolbox/dataprocessing/QST.py
Ctoolbox/dataprocessing/__init__.py
Ctoolbox/exp/__init__.py
Ctoolbox/exp/Beforegates/PowerRabi.py
Ctoolbox/exp/Beforegates/QC_anticross.py
Ctoolbox/exp/Beforegates/QC_coupling.py
Ctoolbox/exp/Beforegates/Ramsey.py
Ctoolbox/exp/Beforegates/Ramsey_2D.py
Ctoolbox/exp/Beforegates/Ramsey_test.py
Ctoolbox/exp/Beforegates/S21.py
Ctoolbox/exp/Beforegates/S21_副本.py
Ctoolbox/exp/Beforegates/S21vsFlux.py
Ctoolbox/exp/Beforegates/S21vsFlux_副本.py
Ctoolbox/exp/Beforegates/S21vsPower.py
Ctoolbox/exp/Beforegates/SNRvsbiasnfreq.py
Ctoolbox/exp/Beforegates/Spectrum.py
Ctoolbox/exp/Beforegates/Spectrum_2D.py
Ctoolbox/exp/Beforegates/Spectrum_Coupler.py
Ctoolbox/exp/Beforegates/T1.py
Ctoolbox/exp/Beforegates/T1_2D.py
Ctoolbox/exp/Beforegates/TimeRabi.py
Ctoolbox/exp/Beforegates/TrigD.py
Ctoolbox/exp/Beforegates/TrigD_副本.py
Ctoolbox/exp/Beforegates/__init__.py
Ctoolbox/exp/Beforegates/singleshot.py
Ctoolbox/exp/NA/JPA_Checkgain.py
Ctoolbox/exp/NA/JPA_GainvsPumppara.py
Ctoolbox/exp/NA/JPA_Optgain.py
Ctoolbox/exp/NA/JPA_Phasediagram.py
Ctoolbox/exp/NA/NASpectrum.py
Ctoolbox/exp/NA/S21vsFlux.py
Ctoolbox/exp/NA/S21vsPower.py
Ctoolbox/exp/NA/TL_Overview.py
Ctoolbox/exp/NA/__init__.py
Ctoolbox/exp/Universe/__init__.py
Ctoolbox/exp/Universe/universe_circ.py
Ctoolbox/exp/Universe/universe_circ_副本.py
Ctoolbox/exp/Universe/universe_plot.py
Ctoolbox/topology/__init__.py
Ctoolbox/topology/config.py
Ctoolbox/topology/core.py
Ctoolbox/topology/grouping.py
Ctoolbox/topology/utils.py
Ctoolbox/topology/visualization.py
Ctoolbox-0.0.1.dist-info/METADATA
Ctoolbox-0.0.1.dist-info/WHEEL
Ctoolbox-0.0.1.dist-info/top_level.txt
Ctoolbox-0.0.1.dist-info/RECORD
