Metadata-Version: 2.1
Name: Ctoolbox
Version: 0.0.1
Summary: Initial version for beginners
Author: Jiaxiu Han
Author-email: hanjx@baqis.ac.cn
Classifier: Programming Language :: Python :: 3
Classifier: License :: OSI Approved :: MIT License
Classifier: Operating System :: OS Independent
Requires-Python: >=3.6
